solr/__init__.py
solr/core.py
solr/paginator.py
solrpy-0.9.9.dist-info/METADATA
solrpy-0.9.9.dist-info/WHEEL
solrpy-0.9.9.dist-info/top_level.txt
solrpy-0.9.9.dist-info/RECORD
