Metadata-Version: 2.1
Name: solrpy
Version: 0.9.9
Summary: Client for the Solr search service
Home-page: http://code.google.com/p/solrpy
License: http://opensource.org/licenses/apache2.0.php
Platform: UNKNOWN
